{
  "MEX": {
    "name": "Mexico",
    "name_es": "México",
    "group": "A",
    "elo": 1799,
    "flag": "🇲🇽"
  },
  "KOR": {
    "name": "South Korea",
    "name_es": "Corea del Sur",
    "group": "A",
    "elo": 1781,
    "flag": "🇰🇷"
  },
  "RSA": {
    "name": "South Africa",
    "name_es": "Sudáfrica",
    "group": "A",
    "elo": 1583,
    "flag": "🇿🇦"
  },
  "CZE": {
    "name": "Czechia",
    "name_es": "República Checa",
    "group": "A",
    "elo": 1783,
    "flag": "🇨🇿"
  },
  "CAN": {
    "name": "Canada",
    "name_es": "Canadá",
    "group": "B",
    "elo": 1748,
    "flag": "🇨🇦"
  },
  "SUI": {
    "name": "Switzerland",
    "name_es": "Suiza",
    "group": "B",
    "elo": 1879,
    "flag": "🇨🇭"
  },
  "QAT": {
    "name": "Qatar",
    "name_es": "Catar",
    "group": "B",
    "elo": 1556,
    "flag": "🇶🇦"
  },
  "BIH": {
    "name": "Bosnia and Herzegovina",
    "name_es": "Bosnia-Herzegovina",
    "group": "B",
    "elo": 1709,
    "flag": "🇧🇦"
  },
  "BRA": {
    "name": "Brazil",
    "name_es": "Brasil",
    "group": "C",
    "elo": 1984,
    "flag": "🇧🇷"
  },
  "MAR": {
    "name": "Morocco",
    "name_es": "Marruecos",
    "group": "C",
    "elo": 1878,
    "flag": "🇲🇦"
  },
  "SCO": {
    "name": "Scotland",
    "name_es": "Escocia",
    "group": "C",
    "elo": 1756,
    "flag": "🏴󠁧󠁢󠁳󠁣󠁴󠁿"
  },
  "HAI": {
    "name": "Haiti",
    "name_es": "Haití",
    "group": "C",
    "elo": 1478,
    "flag": "🇭🇹"
  },
  "USA": {
    "name": "USA",
    "name_es": "Estados Unidos",
    "group": "D",
    "elo": 1836,
    "flag": "🇺🇸"
  },
  "AUS": {
    "name": "Australia",
    "name_es": "Australia",
    "group": "D",
    "elo": 1747,
    "flag": "🇦🇺"
  },
  "PAR": {
    "name": "Paraguay",
    "name_es": "Paraguay",
    "group": "D",
    "elo": 1698,
    "flag": "🇵🇾"
  },
  "TUR": {
    "name": "Turkey",
    "name_es": "Turquía",
    "group": "D",
    "elo": 1841,
    "flag": "🇹🇷"
  },
  "GER": {
    "name": "Germany",
    "name_es": "Alemania",
    "group": "E",
    "elo": 1954,
    "flag": "🇩🇪"
  },
  "CUW": {
    "name": "Curaçao",
    "name_es": "Curazao",
    "group": "E",
    "elo": 1487,
    "flag": "🇨🇼"
  },
  "CIV": {
    "name": "Ivory Coast",
    "name_es": "Costa de Marfil",
    "group": "E",
    "elo": 1680,
    "flag": "🇨🇮"
  },
  "ECU": {
    "name": "Ecuador",
    "name_es": "Ecuador",
    "group": "E",
    "elo": 1693,
    "flag": "🇪🇨"
  },
  "NED": {
    "name": "Netherlands",
    "name_es": "Países Bajos",
    "group": "F",
    "elo": 1960,
    "flag": "🇳🇱"
  },
  "JPN": {
    "name": "Japan",
    "name_es": "Japón",
    "group": "F",
    "elo": 1876,
    "flag": "🇯🇵"
  },
  "SWE": {
    "name": "Sweden",
    "name_es": "Suecia",
    "group": "F",
    "elo": 1773,
    "flag": "🇸🇪"
  },
  "TUN": {
    "name": "Tunisia",
    "name_es": "Túnez",
    "group": "F",
    "elo": 1676,
    "flag": "🇹🇳"
  },
  "BEL": {
    "name": "Belgium",
    "name_es": "Bélgica",
    "group": "G",
    "elo": 1898,
    "flag": "🇧🇪"
  },
  "IRN": {
    "name": "Iran",
    "name_es": "Irán",
    "group": "G",
    "elo": 1766,
    "flag": "🇮🇷"
  },
  "EGY": {
    "name": "Egypt",
    "name_es": "Egipto",
    "group": "G",
    "elo": 1717,
    "flag": "🇪🇬"
  },
  "NZL": {
    "name": "New Zealand",
    "name_es": "Nueva Zelanda",
    "group": "G",
    "elo": 1608,
    "flag": "🇳🇿"
  },
  "ESP": {
    "name": "Spain",
    "name_es": "España",
    "group": "H",
    "elo": 2165,
    "flag": "🇪🇸"
  },
  "URU": {
    "name": "Uruguay",
    "name_es": "Uruguay",
    "group": "H",
    "elo": 1912,
    "flag": "🇺🇾"
  },
  "KSA": {
    "name": "Saudi Arabia",
    "name_es": "Arabia Saudí",
    "group": "H",
    "elo": 1653,
    "flag": "🇸🇦"
  },
  "CPV": {
    "name": "Cape Verde",
    "name_es": "Cabo Verde",
    "group": "H",
    "elo": 1635,
    "flag": "🇨🇻"
  },
  "FRA": {
    "name": "France",
    "name_es": "Francia",
    "group": "I",
    "elo": 2082,
    "flag": "🇫🇷"
  },
  "SEN": {
    "name": "Senegal",
    "name_es": "Senegal",
    "group": "I",
    "elo": 1823,
    "flag": "🇸🇳"
  },
  "NOR": {
    "name": "Norway",
    "name_es": "Noruega",
    "group": "I",
    "elo": 1827,
    "flag": "🇳🇴"
  },
  "IRQ": {
    "name": "Iraq",
    "name_es": "Iraq",
    "group": "I",
    "elo": 1588,
    "flag": "🇮🇶"
  },
  "ARG": {
    "name": "Argentina",
    "name_es": "Argentina",
    "group": "J",
    "elo": 2113,
    "flag": "🇦🇷"
  },
  "AUT": {
    "name": "Austria",
    "name_es": "Austria",
    "group": "J",
    "elo": 1818,
    "flag": "🇦🇹"
  },
  "ALG": {
    "name": "Algeria",
    "name_es": "Argelia",
    "group": "J",
    "elo": 1703,
    "flag": "🇩🇿"
  },
  "JOR": {
    "name": "Jordan",
    "name_es": "Jordania",
    "group": "J",
    "elo": 1626,
    "flag": "🇯🇴"
  },
  "POR": {
    "name": "Portugal",
    "name_es": "Portugal",
    "group": "K",
    "elo": 1986,
    "flag": "🇵🇹"
  },
  "COL": {
    "name": "Colombia",
    "name_es": "Colombia",
    "group": "K",
    "elo": 1857,
    "flag": "🇨🇴"
  },
  "UZB": {
    "name": "Uzbekistan",
    "name_es": "Uzbekistán",
    "group": "K",
    "elo": 1644,
    "flag": "🇺🇿"
  },
  "COD": {
    "name": "DR Congo",
    "name_es": "RD Congo",
    "group": "K",
    "elo": 1640,
    "flag": "🇨🇩"
  },
  "ENG": {
    "name": "England",
    "name_es": "Inglaterra",
    "group": "L",
    "elo": 2020,
    "flag": "🏴󠁧󠁢󠁥󠁮󠁧󠁿"
  },
  "CRO": {
    "name": "Croatia",
    "name_es": "Croacia",
    "group": "L",
    "elo": 1933,
    "flag": "🇭🇷"
  },
  "PAN": {
    "name": "Panama",
    "name_es": "Panamá",
    "group": "L",
    "elo": 1742,
    "flag": "🇵🇦"
  },
  "GHA": {
    "name": "Ghana",
    "name_es": "Ghana",
    "group": "L",
    "elo": 1509,
    "flag": "🇬🇭"
  }
}